{
  "_class": "symbolInstance",
  "booleanOperation": -1,
  "clippingMaskMode": 0,
  "do_objectID": "D552FA2B-CD32-4A23-AB75-FDED7DF8EB89",
  "exportOptions": {
    "_class": "exportOptions",
    "do_objectID": "D755A1A8-85F6-4156-B2C4-A8D00AB98B07",
    "exportFormats": [
    ],
    "includedLayerIds": [
    ],
    "layerOptions": 0,
    "shouldTrim": false
  },
  "frame": {
    "_class": "rect",
    "constrainProportions": false,
    "do_objectID": "4843C439-F76F-44C7-A932-272EAA720EB8",
    "height": 16,
    "width": 16,
    "x": 211,
    "y": 71
  },
  "hasClippingMask": false,
  "horizontalSpacing": 0,
  "isFixedToViewport": false,
  "isFlippedHorizontal": false,
  "isFlippedVertical": false,
  "isLocked": false,
  "isVisible": true,
  "layerListExpandedType": 0,
  "name": "send to",
  "nameIsFixed": false,
  "overrideValues": [
  ],
  "resizingConstraint": 63,
  "resizingType": 0,
  "rotation": 0,
  "scale": 1,
  "shouldBreakMaskChain": false,
  "style": {
    "_class": "style",
    "do_objectID": "51C69420-D7B1-4BE2-9DFC-06CAEBD2645E",
    "endMarkerType": 0,
    "miterLimit": 10,
    "startMarkerType": 0,
    "windingRule": 1
  },
  "symbolID": "798A49BF-6B28-44B1-A8DF-7604C655328E",
  "verticalSpacing": 0
}